{"_path":"/net-core/httpclient-log-record","_dir":"net-core","_draft":false,"_partial":false,"_locale":"","title":"HttpClient Log Record","description":"近期使用Net Core寫Web API有使用到","body":{"type":"root","children":[{"type":"element","tag":"h1","props":{"id":"httpclient-log-record"},"children":[{"type":"text","value":"HttpClient Log Record"}]},{"type":"element","tag":"p","props":{},"children":[{"type":"text","value":"近期使用Net Core寫Web API有使用到"}]}],"toc":{"title":"","searchDepth":2,"depth":2,"links":[]}},"_type":"markdown","_id":"content:150.net-core:1.HttpClient Log Record.md","_source":"content","_file":"150.net-core/1.HttpClient Log Record.md","_extension":"md"}